packrepo/__init__.py
packrepo/library.py
packrepo/benchmarks/__init__.py
packrepo/benchmarks/scalability_benchmark.py
packrepo/benchmarks/synthetic_repo_generator.py
packrepo/cli/__init__.py
packrepo/cli/fastpack.py
packrepo/configs/dataset_config_example.json
packrepo/configs/fastpath.yaml
packrepo/docs/__init__.py
packrepo/docs/link_graph.py
packrepo/docs/text_priority.py
packrepo/evaluator/enhanced_matrix_runner.py
packrepo/evaluator/matrix_runner.py
packrepo/evaluator/configs/datasets.json
packrepo/evaluator/configs/example_config.json
packrepo/evaluator/datasets/__init__.py
packrepo/evaluator/datasets/analytics.py
packrepo/evaluator/datasets/curator.py
packrepo/evaluator/datasets/dataset_builder.py
packrepo/evaluator/datasets/generator.py
packrepo/evaluator/datasets/quality.py
packrepo/evaluator/datasets/schema.py
packrepo/evaluator/datasets/validator.py
packrepo/evaluator/harness/__init__.py
packrepo/evaluator/harness/judge.py
packrepo/evaluator/harness/llm_client.py
packrepo/evaluator/harness/runner.py
packrepo/evaluator/harness/scorers.py
packrepo/evaluator/prompts/__init__.py
packrepo/evaluator/prompts/answerer_system.md
packrepo/evaluator/prompts/answerer_user_template.md
packrepo/evaluator/prompts/judge_rubric.md
packrepo/evaluator/qa_harness/qa_runner.py
packrepo/evaluator/scripts/run_evaluation.py
packrepo/evaluator/statistics/__init__.py
packrepo/evaluator/statistics/acceptance_gates.py
packrepo/evaluator/statistics/bootstrap_bca.py
packrepo/evaluator/statistics/comparative_analysis.py
packrepo/evaluator/statistics/effect_size.py
packrepo/evaluator/statistics/fdr.py
packrepo/evaluator/statistics/paired_analysis.py
packrepo/evaluator/statistics/reporting.py
packrepo/evaluator/tests/test_integration.py
packrepo/evaluator/tests/test_llm_client.py
packrepo/fastpath/__init__.py
packrepo/fastpath/bandit_router.py
packrepo/fastpath/base_types.py
packrepo/fastpath/centrality.py
packrepo/fastpath/demotion.py
packrepo/fastpath/diff_packer.py
sibylline_scribe-1.0.0.dist-info/licenses/LICENSE
sibylline_scribe-1.0.0.dist-info/METADATA
sibylline_scribe-1.0.0.dist-info/WHEEL
sibylline_scribe-1.0.0.dist-info/entry_points.txt
sibylline_scribe-1.0.0.dist-info/top_level.txt
sibylline_scribe-1.0.0.dist-info/RECORD
