Metadata-Version: 2.4
Name: sibylline-scribe
Version: 1.0.0
Summary: Advanced repository intelligence system for LLM code analysis with 20-35% improvement in Q&A accuracy
Author-email: Scribe Research Team <contact@scribe.ai>
Maintainer-email: Scribe Research Team <contact@scribe.ai>
License-Expression: 0BSD
Project-URL: Homepage, https://github.com/scribe-ai/scribe-repo
Project-URL: Repository, https://github.com/scribe-ai/scribe-repo
Project-URL: Documentation, https://scribe-repo.readthedocs.io
Project-URL: Bug Reports, https://github.com/scribe-ai/scribe-repo/issues
Project-URL: Research Paper, https://arxiv.org/abs/2024.scribe
Project-URL: ICSE 2025, https://conf.researchr.org/track/icse-2025/icse-2025-research-track
Project-URL: PyPI Package, https://pypi.org/project/sibylline-scribe/
Keywords: llm,code-analysis,repository-intelligence,submodular-optimization,semantic-search,ai,machine-learning,research,icse,scribe
Classifier: Development Status :: 5 - Production/Stable
Classifier: Intended Audience :: Developers
Classifier: Intended Audience :: Science/Research
Classifier: Programming Language :: Python :: 3.10
Classifier: Programming Language :: Python :: 3.11
Classifier: Programming Language :: Python :: 3.12
Classifier: Programming Language :: Python :: 3.13
Classifier: Topic :: Scientific/Engineering :: Artificial Intelligence
Classifier: Topic :: Software Development :: Libraries :: Python Modules
Classifier: Topic :: Text Processing :: Linguistic
Classifier: Topic :: Utilities
Classifier: Operating System :: OS Independent
Requires-Python: >=3.10
License-File: LICENSE
Requires-Dist: numpy>=1.24.0
Requires-Dist: scikit-learn>=1.3.0
Requires-Dist: tiktoken>=0.5.0
Requires-Dist: tree-sitter>=0.20.0
Requires-Dist: tree-sitter-python>=0.20.0
Requires-Dist: tree-sitter-typescript>=0.20.0
Requires-Dist: tree-sitter-go>=0.20.0
Requires-Dist: tree-sitter-javascript>=0.20.0
Requires-Dist: tree-sitter-java>=0.20.0
Requires-Dist: tree-sitter-cpp>=0.20.0
Requires-Dist: psutil>=5.8.0
Requires-Dist: markdown>=3.8.2
Requires-Dist: pygments>=2.19.2
Requires-Dist: click>=8.0.0
Requires-Dist: rich>=13.0.0
Requires-Dist: tqdm>=4.64.0
Requires-Dist: pyyaml>=6.0
Requires-Dist: requests>=2.28.0
Requires-Dist: gitpython>=3.1.0
Provides-Extra: research
Requires-Dist: scipy>=1.10.0; extra == "research"
Requires-Dist: matplotlib>=3.6.0; extra == "research"
Requires-Dist: seaborn>=0.12.0; extra == "research"
Requires-Dist: jupyter>=1.0.0; extra == "research"
Requires-Dist: pandas>=2.0.0; extra == "research"
Requires-Dist: plotly>=5.0.0; extra == "research"
Provides-Extra: evaluation
Requires-Dist: openai>=1.0.0; extra == "evaluation"
Requires-Dist: anthropic>=0.5.0; extra == "evaluation"
Requires-Dist: sentence-transformers>=2.2.0; extra == "evaluation"
Requires-Dist: transformers>=4.25.0; extra == "evaluation"
Requires-Dist: torch>=2.0.0; extra == "evaluation"
Provides-Extra: dev
Requires-Dist: pytest>=7.0.0; extra == "dev"
Requires-Dist: pytest-cov>=4.0.0; extra == "dev"
Requires-Dist: black>=23.0.0; extra == "dev"
Requires-Dist: isort>=5.12.0; extra == "dev"
Requires-Dist: mypy>=1.5.0; extra == "dev"
Requires-Dist: flake8>=6.0.0; extra == "dev"
Requires-Dist: pre-commit>=3.0.0; extra == "dev"
Provides-Extra: all
Requires-Dist: sibylline-scribe[dev,evaluation,research]; extra == "all"
Dynamic: license-file
